optifolio/__init__.py
optifolio/_base.py
optifolio/optifolio.py
optifolio-0.5.0.dist-info/AUTHORS.rst
optifolio-0.5.0.dist-info/LICENSE
optifolio-0.5.0.dist-info/METADATA
optifolio-0.5.0.dist-info/WHEEL
optifolio-0.5.0.dist-info/top_level.txt
optifolio-0.5.0.dist-info/RECORD
