Metadata-Version: 2.1
Name: optifolio
Version: 0.5.0
Summary: OptiFolio is a Python package for portfolio optimization.
Home-page: https://github.com/kristianbonnici/optifolio
Author: Kristian Bonnici
Author-email: kristiandaaniel@gmail.com
License: MIT license
Keywords: optifolio
Platform: UNKNOWN
Classifier: Development Status :: 2 - Pre-Alpha
Classifier: Intended Audience :: Developers
Classifier: License :: OSI Approved :: MIT License
Classifier: Natural Language :: English
Classifier: Programming Language :: Python :: 3
Classifier: Programming Language :: Python :: 3.6
Classifier: Programming Language :: Python :: 3.7
Classifier: Programming Language :: Python :: 3.8
Requires-Python: >=3.6
